example/__init__.py
example/bellstate.py
example/grover.py
example/teleport.py
taichi_q/Engine.py
taichi_q/Gate.py
taichi_q/Qubits.py
taichi_q/__init__.py
tests/__init__.py
tests/test.py
taichi_q-0.0.10.dist-info/LICENSE
taichi_q-0.0.10.dist-info/METADATA
taichi_q-0.0.10.dist-info/WHEEL
taichi_q-0.0.10.dist-info/top_level.txt
taichi_q-0.0.10.dist-info/RECORD
