Metadata-Version: 2.1
Name: taichi-q
Version: 0.0.10
Summary: Taichi-Q: A quantum circuit simulator for both CPU and GPU
Home-page: https://github.com/bughht/Taichi-Q
Author: Haotian Hong
Author-email: bughht@outlook.com
License: Apache License Version 2.0
Keywords: quantum computation simulator
Platform: UNKNOWN
Requires-Python: >3.6
License-File: LICENSE
Requires-Dist: numpy
Requires-Dist: taichi (==1.2.2)
Requires-Dist: matplotlib
Requires-Dist: scipy
